brahmostra/__init__.py
brahmostra/__main__.py
brahmostra/main.py
brahmostra-1.0.dist-info/METADATA
brahmostra-1.0.dist-info/WHEEL
brahmostra-1.0.dist-info/top_level.txt
brahmostra-1.0.dist-info/RECORD
